[{
	"_id": "589addd787463e107eaff174",
	"index": 0,
	"guid": "359d3212-ce6a-48bf-b0aa-2532d14f5f39",
	"isActive": true,
	"balance": "$1,991.83",
	"picture": "http://placehold.it/32x32",
	"age": 30,
	"eyeColor": "blue",
	"name": "Muriel Lott",
	"gender": "female",
	"company": "PARCOE",
	"email": "muriellott@parcoe.com",
	"phone": "+1 (983) 418-2041",
	"address": "623 Hoyt Street, Waverly, Washington, 4681",
	"about": "Fugiat esse reprehenderit nostrud qui minim nulla incididunt occaecat minim proident esse occaecat ex proident. Culpa ea proident aliqua mollit minim qui voluptate veniam irure sit labore mollit. Mollit aliquip aliquip minim ipsum do veniam voluptate reprehenderit commodo. Esse id ea voluptate irure qui eiusmod do quis cillum culpa ipsum.\r\n",
	"registered": "2016-02-05T03:04:35 -03:00",
	"latitude": 82.326947,
	"longitude": 138.959646,
	"tags": [
		"anim",
		"culpa",
		"nostrud",
		"Lorem",
		"deserunt",
		"commodo",
		"qui"
	],
	"friends": [{
		"id": 0,
		"name": "Clark Kline"
	}, {
		"id": 1,
		"name": "Gutierrez Johns"
	}, {
		"id": 2,
		"name": "Toni Copeland"
	}],
	"greeting": "Hello, Muriel Lott! You have 10 unread messages.",
	"favoriteFruit": "strawberry"
}, {
	"_id": "589addd7485b6301dcf684cf",
	"index": 1,
	"guid": "fb046e19-a29c-40e2-94f3-c992a40fed4d",
	"isActive": false,
	"balance": "$2,328.86",
	"picture": "http://placehold.it/32x32",
	"age": 38,
	"eyeColor": "green",
	"name": "Reed Logan",
	"gender": "male",
	"company": "COMTOURS",
	"email": "reedlogan@comtours.com",
	"phone": "+1 (801) 482-3149",
	"address": "334 Batchelder Street, Worcester, Massachusetts, 2966",
	"about": "Nulla dolore ex ex labore. Pariatur elit enim minim ad est culpa excepteur exercitation elit consectetur dolore nulla ut. Enim nostrud est voluptate dolore. Sunt eu labore aliquip labore officia reprehenderit eu magna commodo laboris exercitation eiusmod aute. Qui anim do aute amet dolore aliqua cupidatat mollit. Reprehenderit cillum Lorem minim veniam irure tempor ut pariatur dolor officia. Tempor duis est ad consectetur proident dolor tempor ad velit.\r\n",
	"registered": "2017-01-21T01:57:38 -03:00",
	"latitude": -78.377539,
	"longitude": 96.771964,
	"tags": [
		"dolor",
		"sit",
		"nostrud",
		"do",
		"anim",
		"eiusmod",
		"cupidatat"
	],
	"friends": [{
		"id": 0,
		"name": "Howe Joyner"
	}, {
		"id": 1,
		"name": "Jacobs Larson"
	}, {
		"id": 2,
		"name": "Church Case"
	}],
	"greeting": "Hello, Reed Logan! You have 3 unread messages.",
	"favoriteFruit": "apple"
}, {
	"_id": "589addd7ee748284cb2b1816",
	"index": 2,
	"guid": "69de2bbe-6976-4009-a849-19684c401f85",
	"isActive": false,
	"balance": "$2,716.58",
	"picture": "http://placehold.it/32x32",
	"age": 21,
	"eyeColor": "green",
	"name": "Bobbie Mathews",
	"gender": "female",
	"company": "APPLICA",
	"email": "bobbiemathews@applica.com",
	"phone": "+1 (966) 405-3143",
	"address": "991 Sackman Street, Caron, Maine, 5334",
	"about": "Voluptate nostrud Lorem proident non eiusmod sint nostrud incididunt. Elit labore consequat incididunt cupidatat voluptate ea mollit proident minim excepteur exercitation velit amet. Labore aute esse velit ea excepteur mollit do cupidatat officia sunt proident labore id. Nostrud proident ex ut culpa esse est do.\r\n",
	"registered": "2014-04-26T11:24:33 -03:00",
	"latitude": -31.546267,
	"longitude": 33.768725,
	"tags": [
		"veniam",
		"non",
		"sunt",
		"nostrud",
		"velit",
		"esse",
		"do"
	],
	"friends": [{
		"id": 0,
		"name": "Ava Stanley"
	}, {
		"id": 1,
		"name": "Meagan Joseph"
	}, {
		"id": 2,
		"name": "Bessie Horton"
	}],
	"greeting": "Hello, Bobbie Mathews! You have 1 unread messages.",
	"favoriteFruit": "strawberry"
}, {
	"_id": "589addd727b97f26f6cd63f2",
	"index": 3,
	"guid": "685a36be-eccb-4be3-84aa-fcce76940237",
	"isActive": false,
	"balance": "$1,593.16",
	"picture": "http://placehold.it/32x32",
	"age": 22,
	"eyeColor": "green",
	"name": "Gilmore Hendrix",
	"gender": "male",
	"company": "BOILICON",
	"email": "gilmorehendrix@boilicon.com",
	"phone": "+1 (978) 536-2130",
	"address": "917 Minna Street, Emerald, District Of Columbia, 4497",
	"about": "Nisi commodo sint aute nostrud amet veniam magna do. Nisi aliquip qui velit consectetur Lorem reprehenderit. Dolore enim do ad adipisicing aliqua. Aliquip esse officia ipsum est ut reprehenderit cupidatat commodo duis nostrud commodo ea dolore. Ex nostrud velit mollit in Lorem enim eiusmod deserunt exercitation. Nisi ullamco nisi dolor cupidatat non sint consequat mollit in id. Dolor labore eu deserunt anim aute occaecat irure magna eiusmod.\r\n",
	"registered": "2015-05-20T04:56:02 -03:00",
	"latitude": -8.77465,
	"longitude": -76.56468,
	"tags": [
		"magna",
		"sint",
		"duis",
		"enim",
		"aute",
		"aute",
		"consectetur"
	],
	"friends": [{
		"id": 0,
		"name": "Nelda Gomez"
	}, {
		"id": 1,
		"name": "Rosella Flowers"
	}, {
		"id": 2,
		"name": "Glenna Norman"
	}],
	"greeting": "Hello, Gilmore Hendrix! You have 9 unread messages.",
	"favoriteFruit": "banana"
}, {
	"_id": "589addd7218fba80bc9de6be",
	"index": 4,
	"guid": "ad4d6183-35e4-4934-ac3f-60b3c63c208d",
	"isActive": true,
	"balance": "$1,093.05",
	"picture": "http://placehold.it/32x32",
	"age": 35,
	"eyeColor": "brown",
	"name": "Stella Workman",
	"gender": "female",
	"company": "PERMADYNE",
	"email": "stellaworkman@permadyne.com",
	"phone": "+1 (997) 448-3432",
	"address": "696 Brightwater Avenue, Welda, Mississippi, 9203",
	"about": "Nostrud nulla ea dolore commodo velit minim amet anim veniam. Velit culpa amet ullamco anim incididunt do exercitation exercitation ut enim. Quis aliquip tempor dolore ullamco tempor voluptate mollit cupidatat excepteur. Occaecat officia ea occaecat esse consectetur consequat consequat occaecat enim irure elit consequat dolor. Non nulla dolore aliquip nisi pariatur aliqua in laborum eiusmod duis nostrud labore quis.\r\n",
	"registered": "2015-02-23T10:13:17 -03:00",
	"latitude": -61.377684,
	"longitude": 89.336839,
	"tags": [
		"excepteur",
		"laborum",
		"ipsum",
		"officia",
		"esse",
		"adipisicing",
		"ullamco"
	],
	"friends": [{
		"id": 0,
		"name": "Annie West"
	}, {
		"id": 1,
		"name": "Maryellen Maynard"
	}, {
		"id": 2,
		"name": "Kim Ayala"
	}],
	"greeting": "Hello, Stella Workman! You have 4 unread messages.",
	"favoriteFruit": "banana"
}]